base_lib/__init__.py
base_lib/app/__init__.py
base_lib/app/api/__init__.py
base_lib/app/core/__init__.py
base_lib/app/core/exception/__init__.py
base_lib/app/core/exception/base_exceptions.py
base_lib/configs/__init__.py
base_lib/configs/config.py
base_lib/domain/__init__.py
base_lib/domain/interactor/__init__.py
base_lib/domain/interactor/api_response.py
base_lib/domain/interactor/base_schemas.py
base_lib/domain/interactor/jwt_token_info.py
base_lib/domain/models/__init__.py
base_lib/domain/models/base_models.py
base_lib/domain/models/common/AuthenticationMethods.py
base_lib/domain/models/common/Countries.py
base_lib/domain/models/common/Genders.py
base_lib/domain/models/common/MetricSystems.py
base_lib/domain/models/common/OrganizationTypes.py
base_lib/domain/models/common/Salutations.py
base_lib/domain/models/common/Timezones.py
base_lib/domain/models/common/__init__.py
base_lib/domain/models/platform/CountryToPoliticalGeoHierarchyLevelsMapping.py
base_lib/domain/models/platform/CountryToPoliticalGeoHierarchyLevelsToResourcesMasterMappingData.py
base_lib/domain/models/platform/GeoCropTypeSowingWindowMapping.py
base_lib/domain/models/platform/PlatformRoles.py
base_lib/domain/models/platform/PoliticalGeoHierarchyLevels.py
base_lib/domain/models/platform/__init__.py
base_lib/infra/__init__.py
base_lib/infra/cache/__init__.py
base_lib/infra/db/__init__.py
base_lib/infra/db/mysql_database.py
base_lib/infra/grpc/__init__.py
base_lib/infra/grpc/clients/__init__.py
base_lib/infra/grpc/proto/__init__.py
base_lib/infra/logger/__init__.py
base_lib/infra/logger/logger.py
platform_base_lib-0.1.6.dist-info/LICENSE
platform_base_lib-0.1.6.dist-info/METADATA
platform_base_lib-0.1.6.dist-info/WHEEL
platform_base_lib-0.1.6.dist-info/top_level.txt
platform_base_lib-0.1.6.dist-info/RECORD
