Metadata-Version: 2.2
Name: platform_base_lib
Version: 0.1.6
Summary: Common library for Base Setup
Home-page: https://github.com/KJBNAgtechPlatform/PlatformBaseLib
Author: Utkarsh Raj
Author-email: utkarsh.raj@kjbnlabs.in
License: MIT
Classifier: Programming Language :: Python :: 3.12
Classifier: License :: OSI Approved :: MIT License
Classifier: Operating System :: OS Independent
Requires-Python: >=3.12
License-File: LICENSE
Requires-Dist: aiomysql==0.2.0
Requires-Dist: annotated-types==0.7.0
Requires-Dist: antiorm==1.2.1
Requires-Dist: anyio==4.6.2.post1
Requires-Dist: bcrypt==4.2.1
Requires-Dist: certifi==2024.8.30
Requires-Dist: cffi==1.17.1
Requires-Dist: charset-normalizer==3.4.0
Requires-Dist: click==8.1.7
Requires-Dist: cryptography==44.0.0
Requires-Dist: db==0.1.1
Requires-Dist: dnspython==2.7.0
Requires-Dist: docutils==0.21.2
Requires-Dist: email_validator==2.2.0
Requires-Dist: fastapi==0.115.5
Requires-Dist: fastcrud==0.15.1
Requires-Dist: greenlet==3.1.1
Requires-Dist: grpcio==1.69.0
Requires-Dist: grpcio-tools==1.68.1
Requires-Dist: h11==0.14.0
Requires-Dist: idna==3.10
Requires-Dist: jaraco.classes==3.4.0
Requires-Dist: jaraco.context==6.0.1
Requires-Dist: jaraco.functools==4.1.0
Requires-Dist: jose==1.0.0
Requires-Dist: keyring==25.5.0
Requires-Dist: markdown-it-py==3.0.0
Requires-Dist: mdurl==0.1.2
Requires-Dist: more-itertools==10.5.0
Requires-Dist: nh3==0.2.19
Requires-Dist: packaging==24.2
Requires-Dist: pkginfo==1.12.0
Requires-Dist: protobuf==5.29.1
Requires-Dist: pycparser==2.22
Requires-Dist: pydantic==2.10.2
Requires-Dist: pydantic-settings==2.6.1
Requires-Dist: pydantic_core==2.27.1
Requires-Dist: Pygments==2.18.0
Requires-Dist: PyMySQL==1.1.1
Requires-Dist: python-dotenv==1.0.1
Requires-Dist: readme_renderer==44.0
Requires-Dist: requests==2.32.3
Requires-Dist: requests-toolbelt==1.0.0
Requires-Dist: rfc3986==2.0.0
Requires-Dist: rich==13.9.4
Requires-Dist: security==1.3.1
Requires-Dist: setuptools==75.6.0
Requires-Dist: sniffio==1.3.1
Requires-Dist: SQLAlchemy==2.0.36
Requires-Dist: SQLAlchemy-Utils==0.41.2
Requires-Dist: starlette==0.41.3
Requires-Dist: twine==6.0.1
Requires-Dist: typing_extensions==4.12.2
Requires-Dist: urllib3==2.2.3
Requires-Dist: uvicorn==0.32.1
Requires-Dist: wheel==0.45.1
Requires-Dist: fastapi-cors
Requires-Dist: ruamel.yaml==0.18.10
Requires-Dist: sqladmin==0.20.1
Requires-Dist: alembic==1.14.0
Provides-Extra: dev
Requires-Dist: black==23.3.0; extra == "dev"
Requires-Dist: isort==5.12.0; extra == "dev"
Requires-Dist: pre-commit==3.3.3; extra == "dev"
Dynamic: author
Dynamic: author-email
Dynamic: classifier
Dynamic: description
Dynamic: description-content-type
Dynamic: home-page
Dynamic: requires-dist
Dynamic: requires-python
Dynamic: summary
